ampgo/__init__.py
ampgo/_ampgo.py
ampgo-1.0.1.dist-info/METADATA
ampgo-1.0.1.dist-info/WHEEL
ampgo-1.0.1.dist-info/top_level.txt
ampgo-1.0.1.dist-info/RECORD
