Metadata-Version: 2.1
Name: ampgo
Version: 1.0.1
Summary: Adaptive Memory Programming for Global Optimization
Home-page: https://github.com/dschmitz89/ampgo/
Author: Daniel Schmitz
License: MIT
Platform: UNKNOWN
Requires-Dist: numpy
Requires-Dist: scipy (>1.2)
